orcalink_client/__init__.py
orcalink_client/channel_flow_control.py
orcalink_client/cli.py
orcalink_client/config_loader.py
orcalink_client/coupling_strategies.py
orcalink_client/data_structures.py
orcalink_client/orcalink_client.py
orcalink_client/spring_constraint_calculator.py
orcalink_client/velocity_estimator.py
orcalink_client/bin/orca_config.json
orcalink_client/bin/orcalink
orcalink_client/proto/__init__.py
orcalink_client/proto/orcalink.proto
orca_link-26.1.3.dist-info/METADATA
orca_link-26.1.3.dist-info/WHEEL
orca_link-26.1.3.dist-info/entry_points.txt
orca_link-26.1.3.dist-info/top_level.txt
orca_link-26.1.3.dist-info/RECORD
