Metadata-Version: 2.4
Name: orca-link
Version: 26.1.3
Summary: OrcaLink gRPC Client with MuJoCo-SPH Simulation Integration
Home-page: https://github.com/your-repo/OrcaLink
Author: OrcaLink Team
Author-email: 
License-Expression: LicenseRef-Proprietary
Keywords: orcalink,grpc,mujoco,sph,simulation
Classifier: Development Status :: 3 - Alpha
Classifier: Intended Audience :: Developers
Classifier: Intended Audience :: Science/Research
Classifier: Programming Language :: Python :: 3
Classifier: Programming Language :: Python :: 3.10
Classifier: Programming Language :: Python :: 3.11
Classifier: Programming Language :: Python :: 3.12
Classifier: Programming Language :: Python :: 3.13
Classifier: Topic :: Scientific/Engineering
Classifier: Topic :: Software Development :: Libraries :: Python Modules
Requires-Python: >=3.10
Requires-Dist: grpcio>=1.67.0
Requires-Dist: grpcio-tools>=1.67.0
Requires-Dist: protobuf>=6.0
Requires-Dist: numpy
Requires-Dist: scipy
Provides-Extra: dev
Requires-Dist: pytest; extra == "dev"
Requires-Dist: pytest-cov; extra == "dev"
Requires-Dist: black; extra == "dev"
Requires-Dist: flake8; extra == "dev"
Provides-Extra: gym
Requires-Dist: gymnasium; extra == "gym"
Requires-Dist: orca-gym; extra == "gym"
Dynamic: home-page
Dynamic: requires-python
